<Annotation>
	<filename>Lair---Great-Room_motion_20230623T121805_8m17.1s.mp4-01495.jpeg</filename>
	<size>
		<width>1920</width>
		<height>1080</height>
		<depth>3</depth>
	</size>
	<object>
		<name>person</name>
		<bndbox>
			<xmin>1042</xmin>
			<xmax>1261</xmax>
			<ymin>573</ymin>
			<ymax>994</ymax>
		</bndbox>
	</object>
	<object>
		<name>person</name>
		<bndbox>
			<xmin>641</xmin>
			<xmax>733</xmax>
			<ymin>207</ymin>
			<ymax>396</ymax>
		</bndbox>
	</object>
	<object>
		<name>person</name>
		<bndbox>
			<xmin>1357</xmin>
			<xmax>1461</xmax>
			<ymin>496</ymin>
			<ymax>656</ymax>
		</bndbox>
	</object>
	<object>
		<name>person</name>
		<bndbox>
			<xmin>714</xmin>
			<xmax>792</xmax>
			<ymin>211</ymin>
			<ymax>402</ymax>
		</bndbox>
	</object>
	<update_record>
		<user>test</user>
		<timestamp>1737369544</timestamp>
	</update_record>
	<last_update_ts>1737369544</last_update_ts>
</Annotation>