<Annotation>
	<filename>Kamera_motion_20240617T211849_1m55.5s.mp4-00682.jpeg</filename>
	<size>
		<width>1920</width>
		<height>1080</height>
		<depth>3</depth>
	</size>
	<object>
		<name>person</name>
		<bndbox>
			<xmin>1538</xmin>
			<xmax>1621</xmax>
			<ymin>500</ymin>
			<ymax>743</ymax>
		</bndbox>
		<fall_status></fall_status>
	</object>
	<update_record>
		<user>xueqing</user>
		<timestamp>1754984041</timestamp>
	</update_record>
	<last_update_ts>1754984041</last_update_ts>
</Annotation>