<Annotation>
	<filename>partsplus-Back-Door_20230921T102952_9m30.9s.mp4-00151.jpeg</filename>
	<size>
		<width>1920</width>
		<height>1080</height>
		<depth>3</depth>
	</size>
	<object>
		<name>car</name>
		<bndbox>
			<xmin>1305</xmin>
			<xmax>1597</xmax>
			<ymin>135</ymin>
			<ymax>498</ymax>
		</bndbox>
	</object>
	<object>
		<name>person</name>
		<bndbox>
			<xmin>1496</xmin>
			<xmax>1724</xmax>
			<ymin>514</ymin>
			<ymax>924</ymax>
		</bndbox>
	</object>
	<update_record>
		<user>test</user>
		<timestamp>1744968990</timestamp>
	</update_record>
	<last_update_ts>1744968990</last_update_ts>
</Annotation>