<Annotation>
	<filename>CAM-14_motion_20240814T073049_39.9s.mp4-00313.jpeg</filename>
	<size>
		<width>1920</width>
		<height>1080</height>
		<depth>3</depth>
	</size>
	<object>
		<name>person</name>
		<bndbox>
			<xmin>1395</xmin>
			<xmax>1608</xmax>
			<ymin>423</ymin>
			<ymax>803</ymax>
		</bndbox>
	</object>
	<object>
		<name>person</name>
		<bndbox>
			<xmin>915</xmin>
			<xmax>1196</xmax>
			<ymin>745</ymin>
			<ymax>1001</ymax>
		</bndbox>
	</object>
	<object>
		<name>person</name>
		<bndbox>
			<xmin>1202</xmin>
			<xmax>1388</xmax>
			<ymin>448</ymin>
			<ymax>819</ymax>
		</bndbox>
	</object>
	<object>
		<name>person</name>
		<bndbox>
			<xmin>1045</xmin>
			<xmax>1196</xmax>
			<ymin>446</ymin>
			<ymax>798</ymax>
		</bndbox>
	</object>
	<object>
		<name>person</name>
		<bndbox>
			<xmin>307</xmin>
			<xmax>556</xmax>
			<ymin>607</ymin>
			<ymax>807</ymax>
		</bndbox>
	</object>
	<object>
		<name>person</name>
		<bndbox>
			<xmin>590</xmin>
			<xmax>811</xmax>
			<ymin>514</ymin>
			<ymax>672</ymax>
		</bndbox>
	</object>
	<object>
		<name>person</name>
		<bndbox>
			<xmin>918</xmin>
			<xmax>979</xmax>
			<ymin>227</ymin>
			<ymax>349</ymax>
		</bndbox>
	</object>
	<update_record>
		<user>xueqing</user>
		<timestamp>1748330294</timestamp>
	</update_record>
	<last_update_ts>1748330294</last_update_ts>
</Annotation>