<Annotation>
	<filename>1-Green-Room-Pan_20200611T174645_9.2s.mp4-00054.jpeg</filename>
	<size>
		<width>1920</width>
		<height>1080</height>
		<depth>3</depth>
	</size>
	<object>
		<name>car</name>
		<bndbox>
			<xmin>195</xmin>
			<xmax>899</xmax>
			<ymin>402</ymin>
			<ymax>1080</ymax>
		</bndbox>
	</object>
	<object>
		<name>pickup</name>
		<bndbox>
			<xmin>558</xmin>
			<xmax>1036</xmax>
			<ymin>52</ymin>
			<ymax>270</ymax>
		</bndbox>
	</object>
	<object>
		<name>car</name>
		<bndbox>
			<xmin>257</xmin>
			<xmax>384</xmax>
			<ymin>38</ymin>
			<ymax>155</ymax>
		</bndbox>
	</object>
	<object>
		<name>car</name>
		<bndbox>
			<xmin>148</xmin>
			<xmax>270</xmax>
			<ymin>79</ymin>
			<ymax>190</ymax>
		</bndbox>
	</object>
	<update_record>
		<user>test</user>
		<timestamp>1724826517</timestamp>
	</update_record>
	<last_update_ts>1724826517</last_update_ts>
</Annotation>