<Annotation>
	<filename>Driveway_20200611T140549_40.8s.mp4-00030.jpeg</filename>
	<size>
		<width>1920</width>
		<height>1080</height>
		<depth>3</depth>
	</size>
	<object>
		<name>car</name>
		<bndbox>
			<xmin>1292</xmin>
			<xmax>1723</xmax>
			<ymin>496</ymin>
			<ymax>777</ymax>
		</bndbox>
	</object>
	<object>
		<name>car</name>
		<bndbox>
			<xmin>1076</xmin>
			<xmax>1416</xmax>
			<ymin>351</ymin>
			<ymax>542</ymax>
		</bndbox>
	</object>
	<object>
		<name>pickup</name>
		<bndbox>
			<xmin>866</xmin>
			<xmax>1155</xmax>
			<ymin>270</ymin>
			<ymax>389</ymax>
		</bndbox>
	</object>
	<object>
		<name>car</name>
		<bndbox>
			<xmin>709</xmin>
			<xmax>959</xmax>
			<ymin>239</ymin>
			<ymax>354</ymax>
		</bndbox>
	</object>
	<object>
		<name>truck</name>
		<bndbox>
			<xmin>273</xmin>
			<xmax>405</xmax>
			<ymin>187</ymin>
			<ymax>287</ymax>
		</bndbox>
	</object>
	<update_record>
		<user>test</user>
		<timestamp>1724826638</timestamp>
	</update_record>
	<last_update_ts>1724826638</last_update_ts>
</Annotation>