<Annotation>
	<filename>172.16.60.11-live_motion_20240104T192431_21.1s.mp4-00119.jpeg</filename>
	<size>
		<width>1920</width>
		<height>1080</height>
		<depth>3</depth>
	</size>
	<object>
		<name>truck</name>
		<bndbox>
			<xmin>116</xmin>
			<xmax>470</xmax>
			<ymin>69</ymin>
			<ymax>484</ymax>
		</bndbox>
	</object>
	<object>
		<name>truck</name>
		<bndbox>
			<xmin>408</xmin>
			<xmax>748</xmax>
			<ymin>6</ymin>
			<ymax>343</ymax>
		</bndbox>
	</object>
	<object>
		<name>truck</name>
		<bndbox>
			<xmin>974</xmin>
			<xmax>1354</xmax>
			<ymin>0</ymin>
			<ymax>151</ymax>
		</bndbox>
	</object>
	<object>
		<name>car</name>
		<bndbox>
			<xmin>1357</xmin>
			<xmax>1608</xmax>
			<ymin>38</ymin>
			<ymax>179</ymax>
		</bndbox>
	</object>
	<update_record>
		<user>test</user>
		<timestamp>1747821939</timestamp>
	</update_record>
	<last_update_ts>1747821939</last_update_ts>
</Annotation>