<Annotation>
	<filename>Camera-15_motion_20240816T025518_32.7s.mp4-00095.jpeg</filename>
	<size>
		<width>1920</width>
		<height>1080</height>
		<depth>3</depth>
	</size>
	<object>
		<name>car</name>
		<bndbox>
			<xmin>747</xmin>
			<xmax>1284</xmax>
			<ymin>596</ymin>
			<ymax>1013</ymax>
		</bndbox>
		<fall_status></fall_status>
	</object>
	<object>
		<name>car</name>
		<bndbox>
			<xmin>457</xmin>
			<xmax>991</xmax>
			<ymin>706</ymin>
			<ymax>1080</ymax>
		</bndbox>
		<fall_status></fall_status>
	</object>
	<object>
		<name>car</name>
		<bndbox>
			<xmin>1110</xmin>
			<xmax>1510</xmax>
			<ymin>380</ymin>
			<ymax>623</ymax>
		</bndbox>
		<fall_status></fall_status>
	</object>
	<object>
		<name>truck</name>
		<bndbox>
			<xmin>1282</xmin>
			<xmax>1749</xmax>
			<ymin>0</ymin>
			<ymax>185</ymax>
		</bndbox>
		<fall_status></fall_status>
	</object>
	<object>
		<name>car</name>
		<bndbox>
			<xmin>1234</xmin>
			<xmax>1595</xmax>
			<ymin>338</ymin>
			<ymax>517</ymax>
		</bndbox>
		<fall_status></fall_status>
	</object>
	<object>
		<name>car</name>
		<bndbox>
			<xmin>281</xmin>
			<xmax>487</xmax>
			<ymin>307</ymin>
			<ymax>540</ymax>
		</bndbox>
		<fall_status></fall_status>
	</object>
	<object>
		<name>car</name>
		<bndbox>
			<xmin>136</xmin>
			<xmax>303</xmax>
			<ymin>395</ymin>
			<ymax>636</ymax>
		</bndbox>
		<fall_status></fall_status>
	</object>
	<object>
		<name>car</name>
		<bndbox>
			<xmin>419</xmin>
			<xmax>634</xmax>
			<ymin>255</ymin>
			<ymax>440</ymax>
		</bndbox>
		<fall_status></fall_status>
	</object>
	<object>
		<name>car</name>
		<bndbox>
			<xmin>554</xmin>
			<xmax>776</xmax>
			<ymin>206</ymin>
			<ymax>368</ymax>
		</bndbox>
		<fall_status></fall_status>
	</object>
	<object>
		<name>car</name>
		<bndbox>
			<xmin>667</xmin>
			<xmax>888</xmax>
			<ymin>173</ymin>
			<ymax>314</ymax>
		</bndbox>
		<fall_status></fall_status>
	</object>
	<object>
		<name>car</name>
		<bndbox>
			<xmin>773</xmin>
			<xmax>975</xmax>
			<ymin>144</ymin>
			<ymax>261</ymax>
		</bndbox>
		<fall_status></fall_status>
	</object>
	<object>
		<name>car</name>
		<bndbox>
			<xmin>870</xmin>
			<xmax>1063</xmax>
			<ymin>128</ymin>
			<ymax>234</ymax>
		</bndbox>
		<fall_status></fall_status>
	</object>
	<object>
		<name>car</name>
		<bndbox>
			<xmin>335</xmin>
			<xmax>478</xmax>
			<ymin>201</ymin>
			<ymax>343</ymax>
		</bndbox>
		<fall_status></fall_status>
	</object>
	<object>
		<name>car</name>
		<bndbox>
			<xmin>228</xmin>
			<xmax>346</xmax>
			<ymin>246</ymin>
			<ymax>403</ymax>
		</bndbox>
		<fall_status></fall_status>
	</object>
	<object>
		<name>car</name>
		<bndbox>
			<xmin>108</xmin>
			<xmax>227</xmax>
			<ymin>309</ymin>
			<ymax>462</ymax>
		</bndbox>
		<fall_status></fall_status>
	</object>
	<object>
		<name>car</name>
		<bndbox>
			<xmin>963</xmin>
			<xmax>1140</xmax>
			<ymin>111</ymin>
			<ymax>208</ymax>
		</bndbox>
		<fall_status></fall_status>
	</object>
	<object>
		<name>car</name>
		<bndbox>
			<xmin>437</xmin>
			<xmax>592</xmax>
			<ymin>169</ymin>
			<ymax>266</ymax>
		</bndbox>
		<fall_status></fall_status>
	</object>
	<object>
		<name>car</name>
		<bndbox>
			<xmin>1041</xmin>
			<xmax>1194</xmax>
			<ymin>94</ymin>
			<ymax>184</ymax>
		</bndbox>
		<fall_status></fall_status>
	</object>
	<object>
		<name>car</name>
		<bndbox>
			<xmin>1295</xmin>
			<xmax>1410</xmax>
			<ymin>101</ymin>
			<ymax>197</ymax>
		</bndbox>
		<fall_status></fall_status>
	</object>
	<object>
		<name>car</name>
		<bndbox>
			<xmin>1393</xmin>
			<xmax>1507</xmax>
			<ymin>134</ymin>
			<ymax>224</ymax>
		</bndbox>
		<fall_status></fall_status>
	</object>
	<object>
		<name>car</name>
		<bndbox>
			<xmin>13</xmin>
			<xmax>103</xmax>
			<ymin>362</ymin>
			<ymax>476</ymax>
		</bndbox>
		<fall_status></fall_status>
	</object>
	<object>
		<name>car</name>
		<bndbox>
			<xmin>1488</xmin>
			<xmax>1593</xmax>
			<ymin>167</ymin>
			<ymax>262</ymax>
		</bndbox>
		<fall_status></fall_status>
	</object>
	<object>
		<name>car</name>
		<bndbox>
			<xmin>1145</xmin>
			<xmax>1251</xmax>
			<ymin>77</ymin>
			<ymax>160</ymax>
		</bndbox>
		<fall_status></fall_status>
	</object>
	<object>
		<name>car</name>
		<bndbox>
			<xmin>1783</xmin>
			<xmax>1853</xmax>
			<ymin>266</ymin>
			<ymax>372</ymax>
		</bndbox>
		<fall_status></fall_status>
	</object>
	<update_record>
		<user>test</user>
		<timestamp>1747814750</timestamp>
	</update_record>
	<update_record>
		<user>xueqing</user>
		<timestamp>1756977326</timestamp>
	</update_record>
	<last_update_ts>1756977326</last_update_ts>
</Annotation>