<Annotation>
	<filename>camera-driveway_20200901T145556_13.3s.mp4-00085.jpeg</filename>
	<size>
		<width>1920</width>
		<height>1080</height>
		<depth>3</depth>
	</size>
	<object>
		<name>car</name>
		<bndbox>
			<xmin>731</xmin>
			<xmax>864</xmax>
			<ymin>510</ymin>
			<ymax>633</ymax>
		</bndbox>
	</object>
	<object>
		<name>person</name>
		<bndbox>
			<xmin>1069</xmin>
			<xmax>1111</xmax>
			<ymin>619</ymin>
			<ymax>749</ymax>
		</bndbox>
	</object>
	<update_record>
		<user>test</user>
		<timestamp>1722245218</timestamp>
	</update_record>
	<last_update_ts>1722245218</last_update_ts>
</Annotation>