<Annotation>
	<filename>C05-Loiter_motion_20230605T115540_52.4s.mp4-00143.jpeg</filename>
	<size>
		<width>1920</width>
		<height>1080</height>
		<depth>3</depth>
	</size>
	<object>
		<name>person</name>
		<bndbox>
			<xmin>1435</xmin>
			<xmax>1645</xmax>
			<ymin>573</ymin>
			<ymax>985</ymax>
		</bndbox>
	</object>
	<object>
		<name>pickup</name>
		<bndbox>
			<xmin>1269</xmin>
			<xmax>1543</xmax>
			<ymin>255</ymin>
			<ymax>471</ymax>
		</bndbox>
	</object>
	<object>
		<name>car</name>
		<bndbox>
			<xmin>1762</xmin>
			<xmax>1920</xmax>
			<ymin>338</ymin>
			<ymax>587</ymax>
		</bndbox>
	</object>
	<object>
		<name>pickup</name>
		<bndbox>
			<xmin>616</xmin>
			<xmax>910</xmax>
			<ymin>190</ymin>
			<ymax>320</ymax>
		</bndbox>
	</object>
	<object>
		<name>car</name>
		<bndbox>
			<xmin>816</xmin>
			<xmax>1045</xmax>
			<ymin>230</ymin>
			<ymax>360</ymax>
		</bndbox>
	</object>
	<update_record>
		<user>test</user>
		<timestamp>1736332473</timestamp>
	</update_record>
	<last_update_ts>1736332473</last_update_ts>
</Annotation>