<Annotation>
	<filename>Garage_motion_20240824T132626_54.8s.mp4-00229.jpeg</filename>
	<size>
		<width>1909</width>
		<height>1080</height>
		<depth>3</depth>
	</size>
	<object>
		<name>car</name>
		<bndbox>
			<xmin>1274</xmin>
			<xmax>1909</xmax>
			<ymin>505</ymin>
			<ymax>1080</ymax>
		</bndbox>
	</object>
	<object>
		<name>car</name>
		<bndbox>
			<xmin>1261</xmin>
			<xmax>1376</xmax>
			<ymin>274</ymin>
			<ymax>346</ymax>
		</bndbox>
	</object>
	<object>
		<name>person</name>
		<bndbox>
			<xmin>1426</xmin>
			<xmax>1493</xmax>
			<ymin>398</ymin>
			<ymax>514</ymax>
		</bndbox>
	</object>
	<update_record>
		<user>test</user>
		<timestamp>1747807507</timestamp>
	</update_record>
	<last_update_ts>1747807507</last_update_ts>
</Annotation>