<Annotation>
	<filename>1-Driveway_20200812T080349_28.3s.mp4-00025.jpeg</filename>
	<size>
		<width>1920</width>
		<height>1080</height>
		<depth>3</depth>
	</size>
	<object>
		<name>car</name>
		<bndbox>
			<xmin>294</xmin>
			<xmax>982</xmax>
			<ymin>431</ymin>
			<ymax>1080</ymax>
		</bndbox>
	</object>
	<object>
		<name>car</name>
		<bndbox>
			<xmin>1135</xmin>
			<xmax>1709</xmax>
			<ymin>606</ymin>
			<ymax>1080</ymax>
		</bndbox>
	</object>
	<object>
		<name>car</name>
		<bndbox>
			<xmin>128</xmin>
			<xmax>503</xmax>
			<ymin>340</ymin>
			<ymax>538</ymax>
		</bndbox>
	</object>
	<object>
		<name>car</name>
		<bndbox>
			<xmin>0</xmin>
			<xmax>165</xmax>
			<ymin>215</ymin>
			<ymax>350</ymax>
		</bndbox>
	</object>
	<object>
		<name>pickup</name>
		<bndbox>
			<xmin>397</xmin>
			<xmax>529</xmax>
			<ymin>58</ymin>
			<ymax>174</ymax>
		</bndbox>
	</object>
	<object>
		<name>car</name>
		<bndbox>
			<xmin>292</xmin>
			<xmax>422</xmax>
			<ymin>80</ymin>
			<ymax>185</ymax>
		</bndbox>
	</object>
	<object>
		<name>car</name>
		<bndbox>
			<xmin>671</xmin>
			<xmax>783</xmax>
			<ymin>9</ymin>
			<ymax>122</ymax>
		</bndbox>
	</object>
	<object>
		<name>car</name>
		<bndbox>
			<xmin>810</xmin>
			<xmax>915</xmax>
			<ymin>11</ymin>
			<ymax>106</ymax>
		</bndbox>
	</object>
	<update_record>
		<user>test</user>
		<timestamp>1724235878</timestamp>
	</update_record>
	<last_update_ts>1724235878</last_update_ts>
</Annotation>