<Annotation>
	<filename>Corner-of-Spa_motion_20240302T212715_1m40.1s.mp4-00544.jpeg</filename>
	<size>
		<width>1909</width>
		<height>1080</height>
		<depth>3</depth>
	</size>
	<object>
		<name>car</name>
		<bndbox>
			<xmin>564</xmin>
			<xmax>1055</xmax>
			<ymin>383</ymin>
			<ymax>667</ymax>
		</bndbox>
	</object>
	<object>
		<name>car</name>
		<bndbox>
			<xmin>1550</xmin>
			<xmax>1908</xmax>
			<ymin>349</ymin>
			<ymax>611</ymax>
		</bndbox>
	</object>
	<object>
		<name>car</name>
		<bndbox>
			<xmin>1372</xmin>
			<xmax>1541</xmax>
			<ymin>318</ymin>
			<ymax>383</ymax>
		</bndbox>
	</object>
	<update_record>
		<user>test</user>
		<timestamp>1751264893</timestamp>
	</update_record>
	<last_update_ts>1751264893</last_update_ts>
</Annotation>