<Annotation>
	<filename>Fenced-area_motion_20240531T003438_16s.mp4-00142.jpeg</filename>
	<size>
		<width>1920</width>
		<height>1080</height>
		<depth>3</depth>
	</size>
	<object>
		<name>person</name>
		<bndbox>
			<xmin>451</xmin>
			<xmax>686</xmax>
			<ymin>329</ymin>
			<ymax>835</ymax>
		</bndbox>
		<fall_status></fall_status>
	</object>
	<update_record>
		<user>zexuan</user>
		<timestamp>1755153934</timestamp>
	</update_record>
	<update_record>
		<user>xueqing</user>
		<timestamp>1755586091</timestamp>
	</update_record>
	<last_update_ts>1755586091</last_update_ts>
</Annotation>