<Annotation>
	<filename>Outdoor---Backyard_motion_20240706T200944_59.2s.mp4-00430.jpeg</filename>
	<size>
		<width>1920</width>
		<height>1080</height>
		<depth>3</depth>
	</size>
	<object>
		<name>person</name>
		<bndbox>
			<xmin>1291</xmin>
			<xmax>1376</xmax>
			<ymin>119</ymin>
			<ymax>356</ymax>
		</bndbox>
		<fall_status></fall_status>
	</object>
	<update_record>
		<user>xueqing</user>
		<timestamp>1753781082</timestamp>
	</update_record>
	<last_update_ts>1753781082</last_update_ts>
</Annotation>