<Annotation>
	<filename>AGC-Entrance_motion_20240703T142910_1m35.1s.mp4-02022.jpeg</filename>
	<size>
		<width>1920</width>
		<height>1080</height>
		<depth>3</depth>
	</size>
	<object>
		<name>person</name>
		<bndbox>
			<xmin>189</xmin>
			<xmax>714</xmax>
			<ymin>270</ymin>
			<ymax>1024</ymax>
		</bndbox>
		<fall_status></fall_status>
	</object>
	<object>
		<name>person</name>
		<bndbox>
			<xmin>1115</xmin>
			<xmax>1611</xmax>
			<ymin>574</ymin>
			<ymax>1080</ymax>
		</bndbox>
		<fall_status></fall_status>
	</object>
	<update_record>
		<user>xueqing</user>
		<timestamp>1753844683</timestamp>
	</update_record>
	<last_update_ts>1753844683</last_update_ts>
</Annotation>