<Annotation>
	<filename>C01_20231108T171626_1m40.6s.mp4-00124.jpeg</filename>
	<size>
		<width>1920</width>
		<height>1080</height>
		<depth>3</depth>
	</size>
	<object>
		<name>person</name>
		<bndbox>
			<xmin>889</xmin>
			<xmax>1069</xmax>
			<ymin>198</ymin>
			<ymax>634</ymax>
		</bndbox>
	</object>
	<object>
		<name>truck</name>
		<bndbox>
			<xmin>99</xmin>
			<xmax>295</xmax>
			<ymin>157</ymin>
			<ymax>369</ymax>
		</bndbox>
	</object>
	<object>
		<name>car</name>
		<bndbox>
			<xmin>531</xmin>
			<xmax>748</xmax>
			<ymin>39</ymin>
			<ymax>162</ymax>
		</bndbox>
	</object>
	<update_record>
		<user>test</user>
		<timestamp>1744967947</timestamp>
	</update_record>
	<last_update_ts>1744967947</last_update_ts>
</Annotation>