<Annotation>
	<filename>CAM-14_motion_20240814T073817_35.6s.mp4-00434.jpeg</filename>
	<size>
		<width>1920</width>
		<height>1080</height>
		<depth>3</depth>
	</size>
	<object>
		<name>person</name>
		<bndbox>
			<xmin>1465</xmin>
			<xmax>1774</xmax>
			<ymin>594</ymin>
			<ymax>1042</ymax>
		</bndbox>
		<fall_status></fall_status>
	</object>
	<object>
		<name>person</name>
		<bndbox>
			<xmin>301</xmin>
			<xmax>583</xmax>
			<ymin>531</ymin>
			<ymax>876</ymax>
		</bndbox>
		<fall_status></fall_status>
	</object>
	<object>
		<name>person</name>
		<bndbox>
			<xmin>758</xmin>
			<xmax>980</xmax>
			<ymin>488</ymin>
			<ymax>900</ymax>
		</bndbox>
		<fall_status></fall_status>
	</object>
	<object>
		<name>person</name>
		<bndbox>
			<xmin>1484</xmin>
			<xmax>1702</xmax>
			<ymin>470</ymin>
			<ymax>838</ymax>
		</bndbox>
		<fall_status></fall_status>
	</object>
	<object>
		<name>person</name>
		<bndbox>
			<xmin>562</xmin>
			<xmax>777</xmax>
			<ymin>511</ymin>
			<ymax>872</ymax>
		</bndbox>
		<fall_status></fall_status>
	</object>
	<object>
		<name>person</name>
		<bndbox>
			<xmin>397</xmin>
			<xmax>639</xmax>
			<ymin>813</ymin>
			<ymax>1080</ymax>
		</bndbox>
		<fall_status></fall_status>
	</object>
	<object>
		<name>person</name>
		<bndbox>
			<xmin>903</xmin>
			<xmax>1047</xmax>
			<ymin>416</ymin>
			<ymax>787</ymax>
		</bndbox>
		<fall_status></fall_status>
	</object>
	<object>
		<name>person</name>
		<bndbox>
			<xmin>925</xmin>
			<xmax>1087</xmax>
			<ymin>301</ymin>
			<ymax>539</ymax>
		</bndbox>
		<fall_status></fall_status>
	</object>
	<object>
		<name>person</name>
		<bndbox>
			<xmin>1138</xmin>
			<xmax>1327</xmax>
			<ymin>487</ymin>
			<ymax>671</ymax>
		</bndbox>
		<fall_status></fall_status>
	</object>
	<object>
		<name>person</name>
		<bndbox>
			<xmin>169</xmin>
			<xmax>389</xmax>
			<ymin>722</ymin>
			<ymax>867</ymax>
		</bndbox>
		<fall_status></fall_status>
	</object>
	<object>
		<name>person</name>
		<bndbox>
			<xmin>1450</xmin>
			<xmax>1547</xmax>
			<ymin>304</ymin>
			<ymax>508</ymax>
		</bndbox>
		<fall_status></fall_status>
	</object>
	<object>
		<name>person</name>
		<bndbox>
			<xmin>1166</xmin>
			<xmax>1248</xmax>
			<ymin>277</ymin>
			<ymax>516</ymax>
		</bndbox>
		<fall_status></fall_status>
	</object>
	<object>
		<name>person</name>
		<bndbox>
			<xmin>643</xmin>
			<xmax>772</xmax>
			<ymin>520</ymin>
			<ymax>663</ymax>
		</bndbox>
		<fall_status></fall_status>
	</object>
	<object>
		<name>person</name>
		<bndbox>
			<xmin>1369</xmin>
			<xmax>1490</xmax>
			<ymin>434</ymin>
			<ymax>553</ymax>
		</bndbox>
		<fall_status></fall_status>
	</object>
	<object>
		<name>person</name>
		<bndbox>
			<xmin>1041</xmin>
			<xmax>1112</xmax>
			<ymin>256</ymin>
			<ymax>416</ymax>
		</bndbox>
		<fall_status></fall_status>
	</object>
	<object>
		<name>person</name>
		<bndbox>
			<xmin>1132</xmin>
			<xmax>1195</xmax>
			<ymin>269</ymin>
			<ymax>424</ymax>
		</bndbox>
		<fall_status></fall_status>
	</object>
	<update_record>
		<user>xueqing</user>
		<timestamp>1751427272</timestamp>
	</update_record>
	<update_record>
		<user>zexuan</user>
		<timestamp>1757494159</timestamp>
	</update_record>
	<update_record>
		<user>xueqing</user>
		<timestamp>1759025045</timestamp>
	</update_record>
	<last_update_ts>1759025045</last_update_ts>
</Annotation>