<Annotation>
	<filename>CAM-14_motion_20240814T072519_39.2s.mp4-00226.jpeg</filename>
	<size>
		<width>1920</width>
		<height>1080</height>
		<depth>3</depth>
	</size>
	<object>
		<name>person</name>
		<bndbox>
			<xmin>1429</xmin>
			<xmax>1703</xmax>
			<ymin>542</ymin>
			<ymax>794</ymax>
		</bndbox>
		<fall_status></fall_status>
	</object>
	<object>
		<name>person</name>
		<bndbox>
			<xmin>441</xmin>
			<xmax>669</xmax>
			<ymin>845</ymin>
			<ymax>1080</ymax>
		</bndbox>
		<fall_status></fall_status>
	</object>
	<object>
		<name>person</name>
		<bndbox>
			<xmin>302</xmin>
			<xmax>548</xmax>
			<ymin>607</ymin>
			<ymax>800</ymax>
		</bndbox>
		<fall_status></fall_status>
	</object>
	<object>
		<name>person</name>
		<bndbox>
			<xmin>1163</xmin>
			<xmax>1329</xmax>
			<ymin>477</ymin>
			<ymax>709</ymax>
		</bndbox>
		<fall_status></fall_status>
	</object>
	<object>
		<name>person</name>
		<bndbox>
			<xmin>591</xmin>
			<xmax>810</xmax>
			<ymin>512</ymin>
			<ymax>666</ymax>
		</bndbox>
		<fall_status></fall_status>
	</object>
	<object>
		<name>person</name>
		<bndbox>
			<xmin>168</xmin>
			<xmax>385</xmax>
			<ymin>723</ymin>
			<ymax>868</ymax>
		</bndbox>
		<fall_status></fall_status>
	</object>
	<object>
		<name>person</name>
		<bndbox>
			<xmin>1141</xmin>
			<xmax>1258</xmax>
			<ymin>325</ymin>
			<ymax>568</ymax>
		</bndbox>
		<fall_status></fall_status>
	</object>
	<object>
		<name>person</name>
		<bndbox>
			<xmin>1016</xmin>
			<xmax>1121</xmax>
			<ymin>342</ymin>
			<ymax>606</ymax>
		</bndbox>
		<fall_status></fall_status>
	</object>
	<object>
		<name>person</name>
		<bndbox>
			<xmin>1539</xmin>
			<xmax>1664</xmax>
			<ymin>470</ymin>
			<ymax>575</ymax>
		</bndbox>
		<fall_status></fall_status>
	</object>
	<object>
		<name>person</name>
		<bndbox>
			<xmin>1379</xmin>
			<xmax>1498</xmax>
			<ymin>463</ymin>
			<ymax>565</ymax>
		</bndbox>
		<fall_status></fall_status>
	</object>
	<object>
		<name>person</name>
		<bndbox>
			<xmin>1271</xmin>
			<xmax>1382</xmax>
			<ymin>435</ymin>
			<ymax>536</ymax>
		</bndbox>
		<fall_status></fall_status>
	</object>
	<object>
		<name>person</name>
		<bndbox>
			<xmin>887</xmin>
			<xmax>961</xmax>
			<ymin>229</ymin>
			<ymax>345</ymax>
		</bndbox>
		<fall_status></fall_status>
	</object>
	<object>
		<name>person</name>
		<bndbox>
			<xmin>1304</xmin>
			<xmax>1370</xmax>
			<ymin>294</ymin>
			<ymax>375</ymax>
		</bndbox>
		<fall_status></fall_status>
	</object>
	<object>
		<name>person</name>
		<bndbox>
			<xmin>948</xmin>
			<xmax>1011</xmax>
			<ymin>259</ymin>
			<ymax>327</ymax>
		</bndbox>
		<fall_status></fall_status>
	</object>
	<object>
		<name>person</name>
		<bndbox>
			<xmin>1174</xmin>
			<xmax>1243</xmax>
			<ymin>282</ymin>
			<ymax>337</ymax>
		</bndbox>
		<fall_status></fall_status>
	</object>
	<object>
		<name>person</name>
		<bndbox>
			<xmin>1251</xmin>
			<xmax>1305</xmax>
			<ymin>289</ymin>
			<ymax>351</ymax>
		</bndbox>
		<fall_status></fall_status>
	</object>
	<update_record>
		<user>test</user>
		<timestamp>1748249555</timestamp>
	</update_record>
	<update_record>
		<user>xueqing</user>
		<timestamp>1757059162</timestamp>
	</update_record>
	<update_record>
		<user>zexuan</user>
		<timestamp>1758191165</timestamp>
	</update_record>
	<update_record>
		<user>xueqing</user>
		<timestamp>1759126575</timestamp>
	</update_record>
	<last_update_ts>1759126575</last_update_ts>
</Annotation>