<Annotation>
	<filename>CAM-14_motion_20240814T072329_34.3s.mp4-00020.jpeg</filename>
	<size>
		<width>1920</width>
		<height>1080</height>
		<depth>3</depth>
	</size>
	<object>
		<name>person</name>
		<bndbox>
			<xmin>461</xmin>
			<xmax>721</xmax>
			<ymin>570</ymin>
			<ymax>1003</ymax>
		</bndbox>
		<fall_status></fall_status>
	</object>
	<object>
		<name>person</name>
		<bndbox>
			<xmin>1488</xmin>
			<xmax>1703</xmax>
			<ymin>551</ymin>
			<ymax>796</ymax>
		</bndbox>
		<fall_status></fall_status>
	</object>
	<object>
		<name>person</name>
		<bndbox>
			<xmin>1169</xmin>
			<xmax>1342</xmax>
			<ymin>472</ymin>
			<ymax>717</ymax>
		</bndbox>
		<fall_status></fall_status>
	</object>
	<object>
		<name>person</name>
		<bndbox>
			<xmin>164</xmin>
			<xmax>406</xmax>
			<ymin>721</ymin>
			<ymax>868</ymax>
		</bndbox>
		<fall_status></fall_status>
	</object>
	<object>
		<name>person</name>
		<bndbox>
			<xmin>1120</xmin>
			<xmax>1259</xmax>
			<ymin>330</ymin>
			<ymax>577</ymax>
		</bndbox>
		<fall_status></fall_status>
	</object>
	<object>
		<name>person</name>
		<bndbox>
			<xmin>590</xmin>
			<xmax>807</xmax>
			<ymin>510</ymin>
			<ymax>664</ymax>
		</bndbox>
		<fall_status></fall_status>
	</object>
	<object>
		<name>person</name>
		<bndbox>
			<xmin>1015</xmin>
			<xmax>1122</xmax>
			<ymin>383</ymin>
			<ymax>674</ymax>
		</bndbox>
		<fall_status></fall_status>
	</object>
	<object>
		<name>person</name>
		<bndbox>
			<xmin>349</xmin>
			<xmax>531</xmax>
			<ymin>613</ymin>
			<ymax>777</ymax>
		</bndbox>
		<fall_status></fall_status>
	</object>
	<object>
		<name>person</name>
		<bndbox>
			<xmin>1379</xmin>
			<xmax>1507</xmax>
			<ymin>461</ymin>
			<ymax>562</ymax>
		</bndbox>
		<fall_status></fall_status>
	</object>
	<object>
		<name>person</name>
		<bndbox>
			<xmin>1542</xmin>
			<xmax>1660</xmax>
			<ymin>479</ymin>
			<ymax>579</ymax>
		</bndbox>
		<fall_status></fall_status>
	</object>
	<object>
		<name>person</name>
		<bndbox>
			<xmin>1288</xmin>
			<xmax>1378</xmax>
			<ymin>430</ymin>
			<ymax>535</ymax>
		</bndbox>
		<fall_status></fall_status>
	</object>
	<object>
		<name>person</name>
		<bndbox>
			<xmin>897</xmin>
			<xmax>959</xmax>
			<ymin>228</ymin>
			<ymax>342</ymax>
		</bndbox>
		<fall_status></fall_status>
	</object>
	<object>
		<name>person</name>
		<bndbox>
			<xmin>1307</xmin>
			<xmax>1369</xmax>
			<ymin>288</ymin>
			<ymax>372</ymax>
		</bndbox>
		<fall_status></fall_status>
	</object>
	<object>
		<name>person</name>
		<bndbox>
			<xmin>1175</xmin>
			<xmax>1240</xmax>
			<ymin>279</ymin>
			<ymax>341</ymax>
		</bndbox>
		<fall_status></fall_status>
	</object>
	<object>
		<name>person</name>
		<bndbox>
			<xmin>952</xmin>
			<xmax>1011</xmax>
			<ymin>262</ymin>
			<ymax>326</ymax>
		</bndbox>
		<fall_status></fall_status>
	</object>
	<object>
		<name>person</name>
		<bndbox>
			<xmin>1241</xmin>
			<xmax>1304</xmax>
			<ymin>295</ymin>
			<ymax>351</ymax>
		</bndbox>
		<fall_status></fall_status>
	</object>
	<update_record>
		<user>test</user>
		<timestamp>1747981619</timestamp>
	</update_record>
	<update_record>
		<user>xueqing</user>
		<timestamp>1759131663</timestamp>
	</update_record>
	<last_update_ts>1759131663</last_update_ts>
</Annotation>