<Annotation>
	<filename>CAM-14_motion_20240814T072111_14.3s.mp4-00020.jpeg</filename>
	<size>
		<width>1920</width>
		<height>1080</height>
		<depth>3</depth>
	</size>
	<object>
		<name>person</name>
		<bndbox>
			<xmin>1435</xmin>
			<xmax>1699</xmax>
			<ymin>542</ymin>
			<ymax>794</ymax>
		</bndbox>
		<fall_status></fall_status>
	</object>
	<object>
		<name>person</name>
		<bndbox>
			<xmin>727</xmin>
			<xmax>1029</xmax>
			<ymin>745</ymin>
			<ymax>948</ymax>
		</bndbox>
		<fall_status></fall_status>
	</object>
	<object>
		<name>person</name>
		<bndbox>
			<xmin>434</xmin>
			<xmax>714</xmax>
			<ymin>898</ymin>
			<ymax>1080</ymax>
		</bndbox>
		<fall_status></fall_status>
	</object>
	<object>
		<name>person</name>
		<bndbox>
			<xmin>1053</xmin>
			<xmax>1289</xmax>
			<ymin>875</ymin>
			<ymax>1080</ymax>
		</bndbox>
		<fall_status></fall_status>
	</object>
	<object>
		<name>person</name>
		<bndbox>
			<xmin>1169</xmin>
			<xmax>1355</xmax>
			<ymin>479</ymin>
			<ymax>719</ymax>
		</bndbox>
		<fall_status></fall_status>
	</object>
	<object>
		<name>person</name>
		<bndbox>
			<xmin>285</xmin>
			<xmax>464</xmax>
			<ymin>834</ymin>
			<ymax>1025</ymax>
		</bndbox>
		<fall_status></fall_status>
	</object>
	<object>
		<name>person</name>
		<bndbox>
			<xmin>1353</xmin>
			<xmax>1451</xmax>
			<ymin>301</ymin>
			<ymax>475</ymax>
		</bndbox>
		<fall_status></fall_status>
	</object>
	<object>
		<name>person</name>
		<bndbox>
			<xmin>1577</xmin>
			<xmax>1690</xmax>
			<ymin>462</ymin>
			<ymax>567</ymax>
		</bndbox>
		<fall_status></fall_status>
	</object>
	<object>
		<name>person</name>
		<bndbox>
			<xmin>1387</xmin>
			<xmax>1502</xmax>
			<ymin>451</ymin>
			<ymax>552</ymax>
		</bndbox>
		<fall_status></fall_status>
	</object>
	<object>
		<name>person</name>
		<bndbox>
			<xmin>1271</xmin>
			<xmax>1382</xmax>
			<ymin>438</ymin>
			<ymax>539</ymax>
		</bndbox>
		<fall_status></fall_status>
	</object>
	<object>
		<name>person</name>
		<bndbox>
			<xmin>898</xmin>
			<xmax>973</xmax>
			<ymin>228</ymin>
			<ymax>340</ymax>
		</bndbox>
		<fall_status></fall_status>
	</object>
	<object>
		<name>person</name>
		<bndbox>
			<xmin>1177</xmin>
			<xmax>1243</xmax>
			<ymin>279</ymin>
			<ymax>351</ymax>
		</bndbox>
		<fall_status></fall_status>
	</object>
	<object>
		<name>person</name>
		<bndbox>
			<xmin>1310</xmin>
			<xmax>1366</xmax>
			<ymin>295</ymin>
			<ymax>374</ymax>
		</bndbox>
		<fall_status></fall_status>
	</object>
	<object>
		<name>person</name>
		<bndbox>
			<xmin>956</xmin>
			<xmax>1012</xmax>
			<ymin>262</ymin>
			<ymax>326</ymax>
		</bndbox>
		<fall_status></fall_status>
	</object>
	<object>
		<name>person</name>
		<bndbox>
			<xmin>1249</xmin>
			<xmax>1307</xmax>
			<ymin>294</ymin>
			<ymax>352</ymax>
		</bndbox>
		<fall_status></fall_status>
	</object>
	<update_record>
		<user>test</user>
		<timestamp>1748242232</timestamp>
	</update_record>
	<update_record>
		<user>xueqing</user>
		<timestamp>1759123017</timestamp>
	</update_record>
	<last_update_ts>1759123017</last_update_ts>
</Annotation>