<Annotation>
	<filename>Garage_motion_20240614T100821_57.5s.mp4-00006.jpeg</filename>
	<size>
		<width>1920</width>
		<height>1080</height>
		<depth>3</depth>
	</size>
	<object>
		<name>pickup</name>
		<bndbox>
			<xmin>118</xmin>
			<xmax>1378</xmax>
			<ymin>61</ymin>
			<ymax>1080</ymax>
		</bndbox>
		<fall_status></fall_status>
	</object>
	<object>
		<name>car</name>
		<bndbox>
			<xmin>1531</xmin>
			<xmax>1920</xmax>
			<ymin>94</ymin>
			<ymax>835</ymax>
		</bndbox>
		<fall_status></fall_status>
	</object>
	<object>
		<name>car</name>
		<bndbox>
			<xmin>465</xmin>
			<xmax>581</xmax>
			<ymin>58</ymin>
			<ymax>117</ymax>
		</bndbox>
		<fall_status></fall_status>
	</object>
	<object>
		<name>car</name>
		<bndbox>
			<xmin>229</xmin>
			<xmax>313</xmax>
			<ymin>121</ymin>
			<ymax>178</ymax>
		</bndbox>
		<fall_status></fall_status>
	</object>
	<update_record>
		<user>xueqing</user>
		<timestamp>1755065743</timestamp>
	</update_record>
	<last_update_ts>1755065743</last_update_ts>
</Annotation>