<Annotation>
	<filename>Camera-7_motion_20240114T133935_15.5s.mp4-00020.jpeg</filename>
	<size>
		<width>1440</width>
		<height>1080</height>
		<depth>3</depth>
	</size>
	<object>
		<name>car</name>
		<bndbox>
			<xmin>674</xmin>
			<xmax>984</xmax>
			<ymin>133</ymin>
			<ymax>263</ymax>
		</bndbox>
	</object>
	<object>
		<name>car</name>
		<bndbox>
			<xmin>20</xmin>
			<xmax>96</xmax>
			<ymin>265</ymin>
			<ymax>351</ymax>
		</bndbox>
	</object>
	<object>
		<name>car</name>
		<bndbox>
			<xmin>97</xmin>
			<xmax>178</xmax>
			<ymin>230</ymin>
			<ymax>308</ymax>
		</bndbox>
	</object>
	<object>
		<name>car</name>
		<bndbox>
			<xmin>245</xmin>
			<xmax>333</xmax>
			<ymin>175</ymin>
			<ymax>236</ymax>
		</bndbox>
	</object>
	<object>
		<name>car</name>
		<bndbox>
			<xmin>171</xmin>
			<xmax>251</xmax>
			<ymin>203</ymin>
			<ymax>269</ymax>
		</bndbox>
	</object>
	<object>
		<name>car</name>
		<bndbox>
			<xmin>308</xmin>
			<xmax>395</xmax>
			<ymin>158</ymin>
			<ymax>209</ymax>
		</bndbox>
	</object>
	<object>
		<name>car</name>
		<bndbox>
			<xmin>364</xmin>
			<xmax>454</xmax>
			<ymin>142</ymin>
			<ymax>189</ymax>
		</bndbox>
	</object>
	<update_record>
		<user>test</user>
		<timestamp>1747992802</timestamp>
	</update_record>
	<last_update_ts>1747992802</last_update_ts>
</Annotation>