<Annotation>
	<filename>Driveway_motion_20240425T110741_1m46.6s.mp4-00015.jpeg</filename>
	<size>
		<width>1909</width>
		<height>1080</height>
		<depth>3</depth>
	</size>
	<object>
		<name>person</name>
		<bndbox>
			<xmin>1011</xmin>
			<xmax>1064</xmax>
			<ymin>97</ymin>
			<ymax>231</ymax>
		</bndbox>
		<fall_status></fall_status>
	</object>
	<update_record>
		<user>zexuan</user>
		<timestamp>1754472114</timestamp>
	</update_record>
	<update_record>
		<user>xueqing</user>
		<timestamp>1755660186</timestamp>
	</update_record>
	<last_update_ts>1755660186</last_update_ts>
</Annotation>