<Annotation>
	<filename>Front-Drive_motion_20240606T145903_11.8s.mp4-00122.jpeg</filename>
	<size>
		<width>1440</width>
		<height>1080</height>
		<depth>3</depth>
	</size>
	<object>
		<name>car</name>
		<bndbox>
			<xmin>503</xmin>
			<xmax>1160</xmax>
			<ymin>287</ymin>
			<ymax>1080</ymax>
		</bndbox>
		<fall_status></fall_status>
	</object>
	<object>
		<name>person</name>
		<bndbox>
			<xmin>1151</xmin>
			<xmax>1279</xmax>
			<ymin>443</ymin>
			<ymax>634</ymax>
		</bndbox>
		<fall_status></fall_status>
	</object>
	<object>
		<name>car</name>
		<bndbox>
			<xmin>9</xmin>
			<xmax>235</xmax>
			<ymin>56</ymin>
			<ymax>157</ymax>
		</bndbox>
		<fall_status></fall_status>
	</object>
	<update_record>
		<user>xueqing</user>
		<timestamp>1756285040</timestamp>
	</update_record>
	<last_update_ts>1756285040</last_update_ts>
</Annotation>