<Annotation>
	<filename>1-front-porch_20191217T143857_59.2s.mp4-00338.jpeg</filename>
	<size>
		<width>1920</width>
		<height>1080</height>
		<depth>3</depth>
	</size>
	<object>
		<name>truck</name>
		<bndbox>
			<xmin>1265</xmin>
			<xmax>1584</xmax>
			<ymin>164</ymin>
			<ymax>461</ymax>
		</bndbox>
	</object>
	<object>
		<name>person</name>
		<bndbox>
			<xmin>1251</xmin>
			<xmax>1332</xmax>
			<ymin>226</ymin>
			<ymax>365</ymax>
		</bndbox>
	</object>
	<update_record>
		<user>test</user>
		<timestamp>1717581658</timestamp>
	</update_record>
	<last_update_ts>1717581658</last_update_ts>
</Annotation>